youtube_downloader_flysea/__init__.py
youtube_downloader_flysea/__main__.py
youtube_downloader_flysea/command.py
youtube_downloader_flysea/demo.py
youtube_downloader_flysea-0.1.1.dist-info/entry_points.txt
youtube_downloader_flysea-0.1.1.dist-info/METADATA
youtube_downloader_flysea-0.1.1.dist-info/WHEEL
youtube_downloader_flysea-0.1.1.dist-info/RECORD
