Metadata-Version: 2.1
Name: youtube-downloader-flysea
Version: 0.1.1
Summary: Download youtube 1080p video with subtitle
License: MIT
Author: flysea
Author-email: flysea0708@163.com
Requires-Python: >=3.13,<3.14
Classifier: License :: OSI Approved :: MIT License
Classifier: Programming Language :: Python :: 3
Classifier: Programming Language :: Python :: 3.13
Requires-Dist: click (>=8.1.7,<9.0.0)
Requires-Dist: pytubefix (>=8.2.0,<9.0.0)
